pytorch_training_template/__init__.py
pytorch_training_template/checkpoint.py
pytorch_training_template/device.py
pytorch_training_template/metrics.py
pytorch_training_template/training.py
pytorch_training_template/visualization.py
pytorch_training_template-0.1.4.dist-info/METADATA
pytorch_training_template-0.1.4.dist-info/WHEEL
pytorch_training_template-0.1.4.dist-info/top_level.txt
pytorch_training_template-0.1.4.dist-info/RECORD
