Metadata-Version: 2.1
Name: pytorch-training-template
Version: 0.1.4
Summary: A modular PyTorch training template for deep learning tasks
Home-page: https://github.com/yourusername/pytorch-training-template
Author: Your Name
Author-email: your.email@example.com
License: UNKNOWN
Platform: UNKNOWN
Classifier: Programming Language :: Python :: 3
Classifier: License :: OSI Approved :: MIT License
Classifier: Operating System :: OS Independent
Requires-Python: >=3.8
Requires-Dist: torch (>=2.0)
Requires-Dist: torchvision (>=0.15)
Requires-Dist: numpy (>=1.23)
Requires-Dist: matplotlib (>=3.7)
Requires-Dist: tqdm (>=4.65)
